README.md
setup.py
cleandev_postgresql_db.egg-info/PKG-INFO
cleandev_postgresql_db.egg-info/SOURCES.txt
cleandev_postgresql_db.egg-info/dependency_links.txt
cleandev_postgresql_db.egg-info/requires.txt
cleandev_postgresql_db.egg-info/top_level.txt
postgresql_db/__init__.py
postgresql_db/configs.py
postgresql_db/exceptions.py
postgresql_db/inmutables.py
postgresql_db/interfaces.py