Metadata-Version: 2.1
Name: cleandev-postgresql-db
Version: 0.3.2
Summary: Module for handler postgresql more easy
Home-page: https://gitlab.com/cleansoftware/libs/public/cleandev-postgresql-db
Author: Daniel Rodriguez Rodriguez
Author-email: danielrodriguezrodriguez.pks@gmail.com
License: UNKNOWN
Project-URL: Bug Tracker, https://gitlab.com/cleansoftware/libs/public/cleandev-postgresql-db/-/issues
Platform: UNKNOWN
Classifier: Programming Language :: Python :: 3
Classifier: License :: OSI Approved :: MIT License
Classifier: Operating System :: OS Independent
Requires-Python: >=3.9
